kbaselib/__init__.py
kbaselib/filesystem.py
kbaselib/image_processing.py
kbaselib/progress_manager.py
kbaselib-0.0.1.dist-info/LICENSE
kbaselib-0.0.1.dist-info/METADATA
kbaselib-0.0.1.dist-info/WHEEL
kbaselib-0.0.1.dist-info/top_level.txt
kbaselib-0.0.1.dist-info/RECORD
