Metadata-Version: 2.1
Name: kbaselib
Version: 0.0.1
Summary: kbaselib
Home-page: UNKNOWN
Author: Jebin Jolly Abraham
Author-email: jebinjabraham@gmail.com
License: UNKNOWN
Keywords: jebin,jabraham,kbase,automation,python,package,manager
Platform: UNKNOWN
Classifier: Development Status :: 1 - Planning
Classifier: Intended Audience :: Developers
Classifier: Programming Language :: Python :: 3
Classifier: Operating System :: Unix
Classifier: Operating System :: MacOS :: MacOS X
Classifier: Operating System :: Microsoft :: Windows
License-File: LICENSE
